robopanda/__init__.py
robopanda/robopanda.py
robopanda-0.0.2.dist-info/LICENSE
robopanda-0.0.2.dist-info/METADATA
robopanda-0.0.2.dist-info/WHEEL
robopanda-0.0.2.dist-info/top_level.txt
robopanda-0.0.2.dist-info/RECORD
